jp_qcew/__init__.py
jp_qcew/data_process.py
jp_qcew/data_viz.py
jp_qcew/decode.json
jp_qcew/graph.py
jp_qcew-3.0.1.dist-info/METADATA
jp_qcew-3.0.1.dist-info/WHEEL
jp_qcew-3.0.1.dist-info/entry_points.txt
jp_qcew-3.0.1.dist-info/licenses/LICENSE
jp_qcew-3.0.1.dist-info/RECORD
