Metadata-Version: 2.4
Name: jp-qcew
Version: 3.0.1
Summary: A python tool to process the Censored QCEW for PR
Author-email: Alejandro Ouslan <alejandro.ouslan@upr.edu>
License-File: LICENSE
Requires-Python: >=3.13
Requires-Dist: duckdb>=1.4.2
Requires-Dist: polars>=1.35.2
Requires-Dist: pyarrow>=22.0.0
